{
 "based_on": "snapshot_date",
 "chart_name": "Available Capacity Trend",
 "chart_type": "Sum",
 "creation": "2026-05-25 02:39:22.078774",
 "currency": "SAR",
 "docstatus": 0,
 "doctype": "Dashboard Chart",
 "document_type": "Accommodation Occupancy Snapshot",
 "filters_json": "[]",
 "group_by_type": "Count",
 "idx": 0,
 "is_public": 1,
 "is_standard": 0,
 "modified": "2026-05-25 02:39:22.078774",
 "modified_by": "Administrator",
 "module": "Habitat",
 "name": "Available Capacity Trend",
 "number_of_groups": 0,
 "owner": "Administrator",
 "roles": [],
 "show_values_over_chart": 0,
 "time_interval": "Monthly",
 "timeseries": 1,
 "timespan": "Last Year",
 "type": "Line",
 "use_report_chart": 0,
 "value_based_on": "available_capacity",
 "y_axis": []
}